with_coordination/__init__.py
with_coordination-0.0.1.dist-info/METADATA
with_coordination-0.0.1.dist-info/WHEEL
with_coordination-0.0.1.dist-info/licenses/LICENSE
with_coordination-0.0.1.dist-info/RECORD
