Metadata-Version: 2.3
Name: with-coordination
Version: 0.0.1
Summary: Declarative coordinated multiple views for Jupyter Widgets
Author-email: Trevor Manz <trevor.j.manz@gmail.com>
License-File: LICENSE
Requires-Python: >=3.8
Requires-Dist: ipywidgets>=8.1.2
Requires-Dist: msgspec>=0.18.6
Requires-Dist: traitlets>=5.14.2
